waf_logs/__init__.py
waf_logs/cloudflare_waf.py
waf_logs/constants.py
waf_logs/db.py
waf_logs/downloader.py
waf_logs/helpers.py
waf_logs/resources/get_firewall_events.graphql
waf_logs/resources/get_firewall_events_ext.graphql
waf_logs/resources/get_firewall_events_restricted.graphql
waf_logs/resources/db/000_logs.sql
waf_logs/resources/db/001_events.sql
waf_logs_cli/__init__.py 
waf_logs_cli/cli.py
waf_logs_cli/resources/.keep
waf_downloader-0.2.24.dist-info/METADATA
waf_downloader-0.2.24.dist-info/WHEEL
waf_downloader-0.2.24.dist-info/entry_points.txt
waf_downloader-0.2.24.dist-info/licenses/LICENSE
waf_downloader-0.2.24.dist-info/RECORD
