Metadata-Version: 2.3
Name: waf_downloader
Version: 0.2.24
Summary: Web Application Firewall logs downloader.
Project-URL: Bug reports, https://github.com/MihaiBojin/waf-downloader/issues/new
Project-URL: Documentation, https://github.com/MihaiBojin/waf-downloader/blob/main/python/README.md
Project-URL: Source, https://github.com/MihaiBojin/waf-downloader
Author-email: Mihai Bojin <557584+MihaiBojin@users.noreply.github.com>
License: Apache-2.0
Keywords: application,cloudflare,download,firewall,logs,waf,web
Classifier: Development Status :: 3 - Alpha
Classifier: Intended Audience :: Developers
Classifier: License :: OSI Approved :: Apache Software License
Classifier: Natural Language :: English
Classifier: Programming Language :: Python :: 3
Classifier: Programming Language :: Python :: 3.9
Classifier: Programming Language :: Python :: 3.10
Classifier: Programming Language :: Python :: 3.11
Classifier: Programming Language :: Python :: 3.12
Classifier: Programming Language :: Python :: 3.13
Requires-Python: >=3.9
Requires-Dist: more-itertools==10.5.0
Requires-Dist: psycopg-binary==3.2.3
Requires-Dist: psycopg-pool==3.2.4
Requires-Dist: psycopg==3.2.3
Requires-Dist: requests==2.32.3
Provides-Extra: cli
Requires-Dist: argparse==1.4.0; extra == 'cli'
Requires-Dist: python-dotenv==1.0.1; extra == 'cli'
Provides-Extra: dev
Requires-Dist: build==1.2.2.post1; extra == 'dev'
Requires-Dist: pip==24.3.1; extra == 'dev'
Requires-Dist: pre-commit==4.0.1; extra == 'dev'
Requires-Dist: pytest==8.3.4; extra == 'dev'
Requires-Dist: toml==0.10.2; extra == 'dev'
Requires-Dist: twine==6.0.1; extra == 'dev'
Requires-Dist: wheel-inspect==1.7.2; extra == 'dev'
Requires-Dist: wheel==0.45.1; extra == 'dev'
